oranda/__init__.py
oranda/cli.py
oranda/command/__init__.py
oranda/exception/__init__.py
oranda-0.1.0.dist-info/LICENSE.txt
oranda-0.1.0.dist-info/METADATA
oranda-0.1.0.dist-info/WHEEL
oranda-0.1.0.dist-info/entry_points.txt
oranda-0.1.0.dist-info/top_level.txt
oranda-0.1.0.dist-info/RECORD
