Metadata-Version: 2.1
Name: oranda
Version: 0.1.0
Summary: A Lightweight and Flexible Ansible Command Line Tool.
Home-page: https://github.com/norwik/oranda/
Author: Clivern
Author-email: hello@clivern.com
License: MIT
Project-URL: Documentation, https://github.com/norwik/oranda/
Project-URL: Source, https://github.com/norwik/oranda/
Project-URL: Changelog, https://github.com/norwik/oranda/blob/main/CHANGELOG.rst
Project-URL: Tracker, https://github.com/norwik/oranda/issues
Project-URL: Download, https://pypi.org/project/oranda/#files
Platform: any
Classifier: Development Status :: 5 - Production/Stable
Classifier: Programming Language :: Python
Classifier: License :: OSI Approved :: MIT License
License-File: LICENSE.txt
Requires-Dist: click (<=8.1.3)
Requires-Dist: ansible-runner (<=2.3.2)
Requires-Dist: importlib-metadata ; python_version < "3.8"
